{"chunk_definitions":[{"row":14,"row_count":1,"visible":true,"expansion_state":0,"options":{"engine":"r","label":"setup","include":false},"document_id":"2BC7DD73","chunk_id":"csetup_chunk","chunk_label":"setup"},{"row":35,"row_count":1,"visible":true,"expansion_state":0,"options":{"engine":"r","label":"unnamed-chunk-29"},"document_id":"2BC7DD73","chunk_id":"c7myuwu6r31i8","chunk_label":"unnamed-chunk-1"},{"row":43,"row_count":1,"visible":true,"expansion_state":0,"options":{"engine":"r","label":"unnamed-chunk-57"},"document_id":"2BC7DD73","chunk_id":"ceu8rvow8rvnw","chunk_label":"unnamed-chunk-2"},{"row":52,"row_count":1,"visible":true,"expansion_state":0,"options":{"engine":"r","label":"unnamed-chunk-35"},"document_id":"2BC7DD73","chunk_id":"cf64ylf7o55iy","chunk_label":"unnamed-chunk-3"},{"row":81,"row_count":1,"visible":true,"expansion_state":0,"options":{"engine":"r","label":"unnamed-chunk-43"},"document_id":"2BC7DD73","chunk_id":"c8n67k503rm7m","chunk_label":"unnamed-chunk-4"},{"row":97,"row_count":1,"visible":true,"expansion_state":0,"options":{"engine":"r","label":"unnamed-chunk-47"},"document_id":"2BC7DD73","chunk_id":"cbu4fvxbvew5w","chunk_label":"unnamed-chunk-5"},{"row":115,"row_count":1,"visible":true,"expansion_state":0,"options":{"engine":"r","label":"unnamed-chunk-51"},"document_id":"2BC7DD73","chunk_id":"c40trgnk4bcvl","chunk_label":"unnamed-chunk-6"},{"row":122,"row_count":1,"visible":true,"expansion_state":0,"options":{"engine":"r","label":"unnamed-chunk-59"},"document_id":"2BC7DD73","chunk_id":"cldihrv58a105","chunk_label":"unnamed-chunk-7"},{"row":131,"row_count":1,"visible":true,"expansion_state":0,"options":{"engine":"r","label":"unnamed-chunk-60"},"document_id":"2BC7DD73","chunk_id":"cgdxlhkfnenm4","chunk_label":"unnamed-chunk-8"},{"row":141,"row_count":1,"visible":true,"expansion_state":0,"options":{"engine":"r","label":"unnamed-chunk-63"},"document_id":"2BC7DD73","chunk_id":"cn25nqlfr3tup","chunk_label":"unnamed-chunk-9"},{"row":151,"row_count":1,"visible":true,"expansion_state":0,"options":{"engine":"r","label":"unnamed-chunk-64"},"document_id":"2BC7DD73","chunk_id":"cefowxf2t82vo","chunk_label":"unnamed-chunk-10"},{"row":161,"row_count":1,"visible":true,"expansion_state":0,"options":{"engine":"r","label":"unnamed-chunk-69"},"document_id":"2BC7DD73","chunk_id":"cbbaljdy1yywl","chunk_label":"unnamed-chunk-11"},{"row":172,"row_count":1,"visible":true,"expansion_state":0,"options":{"engine":"r","label":"unnamed-chunk-72"},"document_id":"2BC7DD73","chunk_id":"cqpdb1tc92kc0","chunk_label":"unnamed-chunk-12"},{"row":182,"row_count":1,"visible":true,"expansion_state":0,"options":{"engine":"r","label":"unnamed-chunk-74"},"document_id":"2BC7DD73","chunk_id":"cutbjyf18mefu","chunk_label":"unnamed-chunk-13"},{"row":225,"row_count":1,"visible":true,"expansion_state":0,"options":{"engine":"r","label":"unnamed-chunk-102"},"document_id":"2BC7DD73","chunk_id":"c1qcae9236hdm","chunk_label":"unnamed-chunk-14"},{"row":250,"row_count":1,"visible":true,"expansion_state":0,"options":{"engine":"r","label":"unnamed-chunk-103"},"document_id":"2BC7DD73","chunk_id":"cp7ninvc62hmo","chunk_label":"unnamed-chunk-15"},{"row":297,"row_count":1,"visible":true,"expansion_state":0,"options":{"engine":"r","label":"unnamed-chunk-126"},"document_id":"2BC7DD73","chunk_id":"c89iqo9ojz24v","chunk_label":"unnamed-chunk-16"},{"row":318,"row_count":1,"visible":true,"expansion_state":0,"options":{"engine":"r","label":"unnamed-chunk-127"},"document_id":"2BC7DD73","chunk_id":"c71kzqdit7c3r","chunk_label":"unnamed-chunk-17"}],"doc_write_time":1732225538,"working_dir":null,"default_chunk_options":{"echo":true},"chunk_rendered_width":700}